sourcespec/__init__.py
sourcespec/_version.py
sourcespec/cached_tiler.py
sourcespec/clipping_detection.py
sourcespec/config.py
sourcespec/kdtree.py
sourcespec/map_tiles.py
sourcespec/plot_sourcepars.py
sourcespec/savefig.py
sourcespec/source_model.py
sourcespec/source_residuals.py
sourcespec/source_spec.py
sourcespec/spectrum.py
sourcespec/ssp_build_spectra.py
sourcespec/ssp_correction.py
sourcespec/ssp_data_types.py
sourcespec/ssp_db_definitions.py
sourcespec/ssp_event.py
sourcespec/ssp_grid_sampling.py
sourcespec/ssp_html_report.py
sourcespec/ssp_inversion.py
sourcespec/ssp_local_magnitude.py
sourcespec/ssp_output.py
sourcespec/ssp_parse_arguments.py
sourcespec/ssp_pick.py
sourcespec/ssp_plot_params_stats.py
sourcespec/ssp_plot_spectra.py
sourcespec/ssp_plot_stacked_spectra.py
sourcespec/ssp_plot_stations.py
sourcespec/ssp_plot_traces.py
sourcespec/ssp_process_traces.py
sourcespec/ssp_qml_output.py
sourcespec/ssp_radiated_energy.py
sourcespec/ssp_radiation_pattern.py
sourcespec/ssp_read_event_metadata.py
sourcespec/ssp_read_sac_header.py
sourcespec/ssp_read_station_metadata.py
sourcespec/ssp_read_traces.py
sourcespec/ssp_residuals.py
sourcespec/ssp_setup.py
sourcespec/ssp_spectral_model.py
sourcespec/ssp_sqlite_output.py
sourcespec/ssp_summary_statistics.py
sourcespec/ssp_update_db.py
sourcespec/ssp_util.py
sourcespec/ssp_wave_arrival.py
sourcespec/adjustText/__init__.py
sourcespec/config_files/configspec.conf
sourcespec/config_files/ssp_event.yaml
sourcespec/configobj/__init__.py
sourcespec/configobj/_version.py
sourcespec/configobj/validate.py
sourcespec/html_report_template/index.html
sourcespec/html_report_template/misfit.html
sourcespec/html_report_template/misfit_table_column.html
sourcespec/html_report_template/quakeml_file_link.html
sourcespec/html_report_template/spectra_plot.html
sourcespec/html_report_template/station_table_row.html
sourcespec/html_report_template/style.css
sourcespec/html_report_template/traces_plot.html
sourcespec-1.8.dist-info/LICENSE.txt
sourcespec-1.8.dist-info/METADATA
sourcespec-1.8.dist-info/WHEEL
sourcespec-1.8.dist-info/entry_points.txt
sourcespec-1.8.dist-info/top_level.txt
sourcespec-1.8.dist-info/RECORD
