Metadata-Version: 2.1
Name: sourcespec
Version: 1.8
Summary: Earthquake source parameters from P- or S-wave displacement spectra
Home-page: https://sourcespec.seismicsource.org
Author: Claudio Satriano
Author-email: satriano@ipgp.fr
License: CeCILL Free Software License Agreement, Version 2.1
Project-URL: Homepage, https://sourcespec.seismicsource.org
Project-URL: Source, https://github.com/SeismicSource/sourcespec
Project-URL: Documentation, https://sourcespec.readthedocs.io
Platform: OS Independent
Classifier: Development Status :: 5 - Production/Stable
Classifier: Environment :: Console
Classifier: Intended Audience :: Science/Research
Classifier: License :: OSI Approved :: CEA CNRS Inria Logiciel Libre License, version 2.1 (CeCILL-2.1)
Classifier: Operating System :: OS Independent
Classifier: Programming Language :: Python
Classifier: Programming Language :: Python :: 3
Classifier: Programming Language :: Python :: 3.7
Classifier: Programming Language :: Python :: 3.8
Classifier: Programming Language :: Python :: 3.9
Classifier: Programming Language :: Python :: 3.10
Classifier: Topic :: Scientific/Engineering
Classifier: Topic :: Scientific/Engineering :: Physics
Requires-Python: >=3.7
License-File: LICENSE.txt
Requires-Dist: numpy >=1.10
Requires-Dist: scipy >=0.17
Requires-Dist: matplotlib >=3.2
Requires-Dist: pillow >=4.0.0
Requires-Dist: obspy >=1.2.0
Requires-Dist: pyproj
Requires-Dist: tzlocal
Requires-Dist: pyyaml >=5.1
Requires-Dist: h5py
